dictpy/__init__.py
dictpy/dict_search.py
dictpy/py.typed
dictpy/serializer.py
dictpy-0.0.7.dist-info/LICENSE.txt
dictpy-0.0.7.dist-info/METADATA
dictpy-0.0.7.dist-info/WHEEL
dictpy-0.0.7.dist-info/top_level.txt
dictpy-0.0.7.dist-info/RECORD
